{
  "apiPrefix": "https://real-estate-redux.herokuapp.com/api",
  "backgroundImagesPrefix": "https://real-estate-redux.herokuapp.com/tutorials",
  "staticUrl": "http://localhost:8050",
  "appTitle": "Re/Max 1st Class Realty, Skokie Homes for Sale, Skokie Real Estate",
  "appType": "website",
  "appUrl": "https://real-estate-redux.herokuapp.com",
  "appImage": "https://cloudinary.com/console/media_library#dialog/image/upload/remax-1st-class-logo_gjc14e",
  "loginUrl": "https://real-estate-redux.herokuapp.com",
  "embedOrigin": "https://real-estate-redux.herokuapp.com",
  "socialAuthURL": "https://real-estate-redux.herokuapp.com/auth/{socialType}",
  "emailAuthURL": "https://real-estate-redux.herokuapp.com/auth/local/",
  "facebookAppId": "",
  "gaTrackingCode": "XXX",
  "companyShareLink": "https://real-estate-redux.herokuapp.com",
  "houseImageThumb": "http://res.cloudinary.com/svitlana/image/upload/v1453494429/house-picture-icon_og71rx.png",
  "ogProps": {
    "homePage": {
      "image": "https://cloudinary.com/console/media_library#dialog/image/upload/remax-1st-class-logo_gjc14e",
      "description": "You Need Only One Company For All Your Real Estate Needs."
    },
    "aboutPage": {
      "url": "https://real-estate-redux.herokuapp.com/about",
      "title": "About Re/Max 1st Class Realty, Skokie, IL",
      "image": "https://cloudinary.com/console/media_library#dialog/image/upload/remax-1st-class-logo_gjc14e",
      "description": "Re/Max 1st Class Realty offers one stop service for home selling or purchase.We can help you find the right specialist to get the lowest mortgage rate and move you to your new home as fast as possible. Our clients always have all papers signed on time with all details covered."
    },
    "contactsPage": {
      "url": "https://real-estate-redux.herokuapp.com/contacts",
      "title": "Contact Re/Max 1st Class Realty Skokie, IL",
      "image": "https://cloudinary.com/console/media_library#dialog/image/upload/remax-1st-class-logo_gjc14e",
      "description": "First class agents for buyers and sellers. Call us for a free consultation!"
    },
    "privacyPolicyPage": {
      "url": "https://real-estate-redux.herokuapp.com/contacts",
      "title": "Re/Max 1st Class Privacy Policy",
      "image": "https://cloudinary.com/console/media_library#dialog/image/upload/remax-1st-class-logo_gjc14e",
      "description": "By visiting or using our website, you agree to the provisions of this privacy policy"
    },
    "termsOfUsePage": {
      "url": "https://real-estate-redux.herokuapp.com/contacts",
      "title": "Please Read Carefully before using Re/Max 1st Class Realty Website",
      "image": "https://cloudinary.com/console/media_library#dialog/image/upload/remax-1st-class-logo_gjc14e",
      "description": "To promote a safe, non-offensive environment for all visitors to our website, we have established these Terms of Use."
    },
    "housesForRentPage": {
      "url": "https://real-estate-redux.herokuapp.com/apartments-for-rent",
      "title": "Northern Illinois Apartments for Rent",
      "image": "https://cloudinary.com/console/media_library#dialog/image/upload/remax-1st-class-logo_gjc14e",
      "description": "Find an Apartment for rent at North and Northwest Chicago Suburbs."
    },
    "housesForSalePage": {
      "url": "https://real-estate-redux.herokuapp.com/apartments-for-sale",
      "title": "Northern Illinois Houses for Sale",
      "image": "https://cloudinary.com/console/media_library#dialog/image/upload/remax-1st-class-logo_gjc14e",
      "description": "Browse Houses for sale at North and Northwest Chicago Suburbs. Detailed listing information with large photos. "
    },
    "cityPage": {
      "url": "https://real-estate-redux.herokuapp.com/apartments-for-sale",
      "title": "North Chicago Suburbs Properties",
      "image": "https://cloudinary.com/console/media_library#dialog/image/upload/remax-1st-class-logo_gjc14e",
      "description": "Find a listing by zip Codes or Property Type. "
    }
  },
  "footerLinks": {
    "twitter": "https://twitter.com/remaxfirstclass",
    "facebook": "https://www.facebook.com/ReMax-1st-Class-Realty-177448822432081",
    "google": "https://plus.google.com/b/101214026615607780081/+Remax1stclass",
    "linkedin": "https://www.linkedin.com/in/re-max-first-class-realty-57707377",
    "youtube": "https://www.youtube.com/channel/UCqlJzj01JS8U3ZUUAFjvxDg"
  }
}